perftask/__init__.py
perftask/builtin.py
perftask/entry.py
perftask/error.py
perftask/graph.py
perftask/help.py
perftask/message.py
perftask/package.py
perftask/task.py
perftask/util.py
perftask/flowctrtask/__init__.py
perftask/flowctrtask/multitask.py
perftask/flowctrtask/repeat.py
perftask/flowctrtask/select.py
perftask/platform/__init__.py
perftask/platform/common.py
perftask/platform/pyver.py
perftask/stdtask/__init__.py
perftask/stdtask/inp.py
perftask/stdtask/prt.py
perftask/stdtask/python.py
perftask/stdtask/read.py
perftask/stdtask/shell.py
perftask/stdtask/write.py
perftask-0.1.37.dist-info/LICENSE
perftask-0.1.37.dist-info/METADATA
perftask-0.1.37.dist-info/WHEEL
perftask-0.1.37.dist-info/entry_points.txt
perftask-0.1.37.dist-info/top_level.txt
perftask-0.1.37.dist-info/RECORD
