Metadata-Version: 2.1
Name: perftask
Version: 0.1.37
Summary: The Tasking Platform
Home-page: UNKNOWN
Author: Youngsung Kim
Author-email: grnydawn@gmail.com
License: UNKNOWN
Platform: UNKNOWN
Classifier: Development Status :: 3 - Alpha
Classifier: Intended Audience :: Developers
Classifier: Programming Language :: Python :: 2
Classifier: Programming Language :: Python :: 2.7
Classifier: Programming Language :: Python :: 3
Classifier: Programming Language :: Python :: 3.5
Classifier: Programming Language :: Python :: 3.6
Classifier: Programming Language :: Python :: 3.7
Requires-Dist: toml
Requires-Dist: virtualenv
Requires-Dist: pipenv
